cce/CCE.py
cce/PCE.py
cce/__init__.py
nv/__init__.py
nv/nv.py
nv/p1.py
p1/__init__.py
p1/p1.py
tools/__init__.py
tools/plot_tools.py
ONV-1.0.3.dist-info/METADATA
ONV-1.0.3.dist-info/WHEEL
ONV-1.0.3.dist-info/top_level.txt
ONV-1.0.3.dist-info/RECORD
