Metadata-Version: 2.1
Name: ONV
Version: 1.0.3
Summary: Package for general NV based simulations
Author: Oliver Whaites
Author-email: o.whaites@btinternet.com
Keywords: NV
Classifier: Development Status :: 3 - Alpha
Classifier: Intended Audience :: Education
Classifier: Programming Language :: Python :: 2
Classifier: Programming Language :: Python :: 3
Classifier: Operating System :: MacOS :: MacOS X
Classifier: Operating System :: Microsoft :: Windows
